[
  {
    "name": "张洪heo",
    "title": "给 SearXNG 接入豆包搜索，解决 OpenClaw 信源难题",
    "link": "https://blog.zhheo.com/p/1ffvrvyd.html",
    "published": 1784264897,
    "isNew": true
  },
  {
    "name": "张洪heo",
    "title": "OpenClaw记忆系统升级：从memory-core到memory-lancedb-pro的迁移与配置",
    "link": "https://blog.zhheo.com/p/0kl9erod.html",
    "published": 1784175473
  },
  {
    "name": "张洪heo",
    "title": "screenpipe：开源本地的 AI 记忆引擎，让电脑更懂你",
    "link": "https://blog.zhheo.com/p/94w0byur.html",
    "published": 1784131200
  },
  {
    "name": "柳神",
    "title": "Cloudflare/Vercel项目推荐(6)",
    "link": "https://blog.liushen.fun/posts/e4a369fc/",
    "published": 1783872720
  },
  {
    "name": "张洪heo",
    "title": "混元hy3模型上手：腾讯送了云函数个人版6个月，怎么才能用上",
    "link": "https://blog.zhheo.com/p/2orxjo9r.html",
    "published": 1783480134
  },
  {
    "name": "张洪heo",
    "title": "给OpenClaw加上rm删除保护：防止AI误删你的整个电脑",
    "link": "https://blog.zhheo.com/p/owiixgnk.html",
    "published": 1783422360
  }
]