[
  {
    "name": "张洪heo",
    "title": "为OpenClaw搭建一个免费的搜索引擎，如何让OpenClaw搜索网页内容",
    "link": "https://blog.zhheo.com/p/9p755adr.html",
    "published": 1779419498,
    "isNew": true
  },
  {
    "name": "张洪heo",
    "title": "这一次，我们听点有意思的",
    "link": "https://blog.zhheo.com/p/7a59rx04.html",
    "published": 1779337636
  },
  {
    "name": "张洪heo",
    "title": "为啥别人用Image2做的图那么好看？我的却特别丑？如何模仿别人的风格作图？",
    "link": "https://blog.zhheo.com/p/viqyx0td.html",
    "published": 1779332533
  },
  {
    "name": "张洪heo",
    "title": "如何给自己创作的歌曲生成歌词文件？手打逐字歌词lrc文件教程",
    "link": "https://blog.zhheo.com/p/rdlrcfqe.html",
    "published": 1779165447
  },
  {
    "name": "张洪heo",
    "title": "免费可商用字体推荐：寒蝉端黑宋下载",
    "link": "https://blog.zhheo.com/p/jsrckoff.html",
    "published": 1779092236
  },
  {
    "name": "柳神",
    "title": "黔山赴夏，清风入怀",
    "link": "https://blog.liushen.fun/posts/1968ba6c/",
    "published": 1777899021
  }
]